rom_operator_inference/__init__.py
rom_operator_inference/errors.py
rom_operator_inference/core/__init__.py
rom_operator_inference/core/_base.py
rom_operator_inference/core/interpolate/__init__.py
rom_operator_inference/core/interpolate/_base.py
rom_operator_inference/core/interpolate/_public.py
rom_operator_inference/core/nonparametric/__init__.py
rom_operator_inference/core/nonparametric/_base.py
rom_operator_inference/core/nonparametric/_frozen.py
rom_operator_inference/core/nonparametric/_public.py
rom_operator_inference/core/operators/__init__.py
rom_operator_inference/core/operators/_affine.py
rom_operator_inference/core/operators/_base.py
rom_operator_inference/core/operators/_interpolate.py
rom_operator_inference/core/operators/_nonparametric.py
rom_operator_inference/lstsq/__init__.py
rom_operator_inference/lstsq/_base.py
rom_operator_inference/lstsq/_tikhonov.py
rom_operator_inference/post/__init__.py
rom_operator_inference/post/_errors.py
rom_operator_inference/pre/__init__.py
rom_operator_inference/pre/_finite_difference.py
rom_operator_inference/pre/_multivar.py
rom_operator_inference/pre/_reprojection.py
rom_operator_inference/pre/basis/__init__.py
rom_operator_inference/pre/basis/_base.py
rom_operator_inference/pre/basis/_linear.py
rom_operator_inference/pre/basis/_pod.py
rom_operator_inference/pre/transform/__init__.py
rom_operator_inference/pre/transform/_base.py
rom_operator_inference/pre/transform/_shiftscale.py
rom_operator_inference/utils/__init__.py
rom_operator_inference/utils/_hdf5.py
rom_operator_inference/utils/_kronecker.py
rom_operator_inference-1.4.1.dist-info/LICENSE
rom_operator_inference-1.4.1.dist-info/METADATA
rom_operator_inference-1.4.1.dist-info/WHEEL
rom_operator_inference-1.4.1.dist-info/top_level.txt
rom_operator_inference-1.4.1.dist-info/RECORD
