Metadata-Version: 2.1
Name: rom-operator-inference
Version: 1.4.1
Summary: Operator inference for data-driven, non-intrusive model reduction of dynamical systems.
Home-page: https://github.com/Willcox-Research-Group/rom-operator-inference-Python3
Author: Willcox Research Group
Maintainer: Shane A. McQuarrie
Maintainer-email: shanemcq@utexas.edu
License: MIT
Platform: UNKNOWN
Classifier: Programming Language :: Python :: 3
Classifier: Natural Language :: English
Classifier: License :: OSI Approved :: MIT License
Classifier: Operating System :: OS Independent
Classifier: Topic :: Scientific/Engineering
Classifier: Intended Audience :: Science/Research
Classifier: Development Status :: 4 - Beta
Requires-Python: >=3.6
License-File: LICENSE
Requires-Dist: h5py (>=2.9.0)
Requires-Dist: numpy (>=1.16)
Requires-Dist: scipy (>=1.3)
Requires-Dist: matplotlib (>=3.0)
Requires-Dist: scikit-learn (>=0.18)
